linear_operator/__init__.py
linear_operator/beta_features.py
linear_operator/settings.py
linear_operator/version.py
linear_operator/functions/__init__.py
linear_operator/functions/_diagonalization.py
linear_operator/functions/_dsmm.py
linear_operator/functions/_inv_quad.py
linear_operator/functions/_inv_quad_logdet.py
linear_operator/functions/_matmul.py
linear_operator/functions/_pivoted_cholesky.py
linear_operator/functions/_root_decomposition.py
linear_operator/functions/_solve.py
linear_operator/functions/_sqrt_inv_matmul.py
linear_operator/operators/__init__.py
linear_operator/operators/_linear_operator.py
linear_operator/operators/added_diag_linear_operator.py
linear_operator/operators/batch_repeat_linear_operator.py
linear_operator/operators/block_diag_linear_operator.py
linear_operator/operators/block_interleaved_linear_operator.py
linear_operator/operators/block_linear_operator.py
linear_operator/operators/cat_linear_operator.py
linear_operator/operators/chol_linear_operator.py
linear_operator/operators/constant_mul_linear_operator.py
linear_operator/operators/dense_linear_operator.py
linear_operator/operators/diag_linear_operator.py
linear_operator/operators/identity_linear_operator.py
linear_operator/operators/interpolated_linear_operator.py
linear_operator/operators/keops_linear_operator.py
linear_operator/operators/kernel_linear_operator.py
linear_operator/operators/kronecker_product_added_diag_linear_operator.py
linear_operator/operators/kronecker_product_linear_operator.py
linear_operator/operators/linear_operator_representation_tree.py
linear_operator/operators/low_rank_root_added_diag_linear_operator.py
linear_operator/operators/low_rank_root_linear_operator.py
linear_operator/operators/masked_linear_operator.py
linear_operator/operators/matmul_linear_operator.py
linear_operator/operators/mul_linear_operator.py
linear_operator/operators/permutation_linear_operator.py
linear_operator/operators/psd_sum_linear_operator.py
linear_operator-0.5.3.dist-info/LICENSE
linear_operator-0.5.3.dist-info/METADATA
linear_operator-0.5.3.dist-info/WHEEL
linear_operator-0.5.3.dist-info/top_level.txt
linear_operator-0.5.3.dist-info/RECORD
