Metadata-Version: 2.1
Name: linear-operator
Version: 0.5.3
Summary: A linear operator implementation, primarily designed for finite-dimensional positive definite operators (i.e. kernel matrices).
Home-page: UNKNOWN
Author: Geoff Pleiss
Author-email: gpleiss@gmail.com
License: MIT
Project-URL: Documentation, https://linear_operator.readthedocs.io
Project-URL: Source, https://github.com/cornellius-gp/linear_operator/
Platform: UNKNOWN
Classifier: Development Status :: 2 - Pre-Alpha
Classifier: Programming Language :: Python :: 3
Requires-Python: >=3.8
Provides-Extra: dev
Provides-Extra: docs
Provides-Extra: test
